newrelic_telemetry_sdk/__init__.py
newrelic_telemetry_sdk/batch.py
newrelic_telemetry_sdk/client.py
newrelic_telemetry_sdk/event.py
newrelic_telemetry_sdk/harvester.py
newrelic_telemetry_sdk/log.py
newrelic_telemetry_sdk/metric.py
newrelic_telemetry_sdk/metric_batch.py
newrelic_telemetry_sdk/span.py
newrelic_telemetry_sdk/version.py
newrelic_telemetry_sdk-0.9.0.dist-info/licenses/LICENSE
newrelic_telemetry_sdk-0.9.0.dist-info/METADATA
newrelic_telemetry_sdk-0.9.0.dist-info/WHEEL
newrelic_telemetry_sdk-0.9.0.dist-info/top_level.txt
newrelic_telemetry_sdk-0.9.0.dist-info/RECORD
